EvolutionaryModelDiscovery/ABMEvaluator.py
EvolutionaryModelDiscovery/Factor.py
EvolutionaryModelDiscovery/FactorGenerator.py
EvolutionaryModelDiscovery/FactorImportances.py
EvolutionaryModelDiscovery/NetLogoWriter.py
EvolutionaryModelDiscovery/PrimitiveSetGenerator.py
EvolutionaryModelDiscovery/SimpleDEAPGP.py
EvolutionaryModelDiscovery/Util.py
EvolutionaryModelDiscovery/__init__.py
EvolutionaryModelDiscovery-2.0.0.dist-info/LICENSE.txt
EvolutionaryModelDiscovery-2.0.0.dist-info/METADATA
EvolutionaryModelDiscovery-2.0.0.dist-info/WHEEL
EvolutionaryModelDiscovery-2.0.0.dist-info/top_level.txt
EvolutionaryModelDiscovery-2.0.0.dist-info/RECORD
