Metadata-Version: 2.1
Name: EvolutionaryModelDiscovery
Version: 2.0.0
Summary: EvolutionaryModelDiscovery: Automated agent rule generation and importance evaluation for agent-based models with Genetic Programming.
Home-page: https://github.com/chathika/EvolutionaryModelDiscovery/
Author: Chathika Gunaratne
Author-email: chathikagunaratne@gmail.com
License: GPL
Project-URL: Source, https://github.com/chathika/EvolutionaryModelDiscovery
Project-URL: Thanks!, http://complexity.cecs.ucf.edu/
Platform: UNKNOWN
Requires-Dist: deap
Requires-Dist: eli5
Requires-Dist: networkx
Requires-Dist: nl4py (>=0.9.0)
Requires-Dist: numpy
Requires-Dist: pandas
Requires-Dist: scikit-learn
Requires-Dist: scipy
